transformers_keras_dataloader/__init__.py
transformers_keras_dataloader/config/__init__.py
transformers_keras_dataloader/config/common_params.json
transformers_keras_dataloader/config/model_vars_params.json
transformers_keras_dataloader/scripts/EmbeddingDataloader.py
transformers_keras_dataloader/scripts/OffsetMapper.py
transformers_keras_dataloader/scripts/PoolPolicy.py
transformers_keras_dataloader/scripts/SentenceEmbedder.py
transformers_keras_dataloader/scripts/WordEmbedder.py
transformers_keras_dataloader/scripts/__init__.py
transformers_keras_dataloader/scripts/util/__init__.py
transformers_keras_dataloader/scripts/util/load_tokenizer_and_model.py
transformers_keras_dataloader-0.0.5.dist-info/LICENSE
transformers_keras_dataloader-0.0.5.dist-info/METADATA
transformers_keras_dataloader-0.0.5.dist-info/WHEEL
transformers_keras_dataloader-0.0.5.dist-info/top_level.txt
transformers_keras_dataloader-0.0.5.dist-info/RECORD
