Metadata-Version: 2.1
Name: transformers-keras-dataloader
Version: 0.0.5
Summary: Transformers Keras Dataloader provides an EmbeddingDataLoader class, a subclass of keras.utils.Sequence which enables real-time embedding generation from pretrained transformer models while feeding it to your Keras model via batches.
Home-page: https://github.com/pratikdk/transformers_keras_dataloader
Author: Pratik Deoolwadikar
Author-email: pratik.deoolwadikar@gmail.com
License: UNKNOWN
Download-URL: https://github.com/pratikdk/transformers_keras_dataloader/archive/v0.0.5.tar.gz
Keywords: transformers,embedding,dataloader,generator,huggingface,attention
Platform: UNKNOWN
Classifier: Programming Language :: Python :: 3
Classifier: License :: OSI Approved :: Apache Software License
Classifier: Operating System :: OS Independent
Requires-Dist: numpy
Requires-Dist: pandas
Requires-Dist: tensorflow
Requires-Dist: keras
Requires-Dist: torch (>=1.2.0)
Requires-Dist: transformers (>=3.0.2)
